LICENSE
MANIFEST.in
README.md
setup.py
debian/changelog
debian/compat
debian/control
debian/rules
debian/source/format
debian/source/options
mp/__init__.py
mp.importer.egg-info/PKG-INFO
mp.importer.egg-info/SOURCES.txt
mp.importer.egg-info/dependency_links.txt
mp.importer.egg-info/requires.txt
mp.importer.egg-info/top_level.txt
mp/importer/__init__.py
mp/importer/batcher.py
mp/importer/cleaner.py
mp/importer/urlname.py
mp/importer/schema/__init__.py
mp/importer/schema/content.rnc
mp/importer/schema/content.rng
mp/importer/stopwords/de.txt
mp/importer/stopwords/en.txt
mp/importer/stopwords/es.txt
mp/importer/tests/__init__.py
mp/importer/tests/test_batcher.py
mp/importer/tests/test_cleaner.py
mp/importer/tests/test_schema.py
mp/importer/tests/test_urlname.py