Metadata-Version: 1.1
Name: mp.importer
Version: 0.10
Summary: Utilities to ease imports of content to MetroPublisher.
Home-page: UNKNOWN
Author: Vanguardistas LLC
Author-email: brian@vanguardistas.net
License: BSD
Platform: UNKNOWN
Classifier: Intended Audience :: Developers
Classifier: Operating System :: OS Independent
Classifier: License :: OSI Approved :: BSD License
Classifier: Programming Language :: Python :: 2
Classifier: Programming Language :: Python :: 2.7
Classifier: Programming Language :: Python :: 3
Classifier: Programming Language :: Python :: 3.4
